{
    "vessel": {
	"name"	: "Plaka",
	"brand"	: "Finngulf",
	"type"	: "28e",
	"uuid"	: "10101011",

	"dimensions": {
	    "length": 8.3,
	    "width": 2.95,
	    "mast": 12.3,
	    "depthTransducer": 0.3,
	    "keel": 1.7
	}
    },

    "interfaces": [
        "rest",
        "bower",
        "ws", "beaglek"
    ],

    "pipedProviders": [{
        "id": "nmeaFromFile",
        "pipeElements": [
            {
                "type": "providers/filestream",
                "options": {
                    "filename": "samples/plaka2.log"
                },
                "optionMappings": [
                    {
                        "fromAppProperty": "argv.nmeafilename",
                        "toOption": "filename"
                    }
                ]
            },
            {
                "type": "providers/throttle",
                "options": {
                    "rate": 500
                }
            },
            {
                "type": "providers/liner"
            },
            {
                "type": "providers/nmea0183-signalk",
                "optionMappings": [
                    {
                        "fromAppProperty": "selfId",
                        "toOption": "selfId"
                    },
                    {
                        "fromAppProperty": "selfType",
                        "toOption": "selfType"
                    }
                ]
            }
        ]
    }]
}
